[
  {
    "restaurant":"Papa Johns",
    "image": "https://wasimpizza.com/wp-content/uploads/2022/02/pizza.png",
    "address": "North California , Street 123, USA",
    "pizzaSelections":[
      {"name":"BBQ Chicken and Bacon",
        "image": "https://wasimpizza.com/wp-content/uploads/2022/02/pizza.png",
        "sizes": [
          {"size":"Eight Inch", "diameter":8, "slicesPerPizza":4, "sliceCalories":240},
          {"size":"Small", "diameter":10, "slicesPerPizza":6, "sliceCalories":230},
          {"size":"Medium", "diameter":12, "slicesPerPizza":8, "sliceCalories":240},
          {"size":"Large", "diameter":14, "slicesPerPizza":8, "sliceCalories":340},
          {"size":"Extra Large", "diameter":16, "slicesPerPizza":10, "sliceCalories":360}
        ]
      },
      {"name":"Cheese",
        "image": "https://wasimpizza.com/wp-content/uploads/2022/02/pizza.png",
        "sizes": [
          {"size":"Eight Inch", "diameter":8, "slicesPerPizza":4, "sliceCalories":200},
          {"size":"Small", "diameter":10, "slicesPerPizza":6, "sliceCalories":180},
          {"size":"Medium", "diameter":12, "slicesPerPizza":8, "sliceCalories":210},
          {"size":"Large", "diameter":14, "slicesPerPizza":8, "sliceCalories":290},
          {"size":"Extra Large", "diameter":16, "slicesPerPizza":10, "sliceCalories":300}
        ]
      },
      {"name":"Pepperoni",
        "image": "https://wasimpizza.com/wp-content/uploads/2022/02/pizza.png",
        "sizes": [
          {"size":"Eight Inch", "diameter":8, "slicesPerPizza":4, "sliceCalories":220},
          {"size":"Small", "diameter":10, "slicesPerPizza":6, "sliceCalories":210},
          {"size":"Medium", "diameter":12, "slicesPerPizza":8, "sliceCalories":220},
          {"size":"Large", "diameter":14, "slicesPerPizza":8, "sliceCalories":320},
          {"size":"Extra Large", "diameter":16, "slicesPerPizza":10, "sliceCalories":330}
        ]
      },
      {"name":"Pepperoni and Sausage",
        "image": "https://wasimpizza.com/wp-content/uploads/2022/02/pizza.png",
        "sizes": [
          {"size":"Eight Inch", "diameter":8, "slicesPerPizza":4, "sliceCalories":250},
          {"size":"Small", "diameter":10, "slicesPerPizza":6, "sliceCalories":240},
          {"size":"Medium", "diameter":12, "slicesPerPizza":8, "sliceCalories":260},
          {"size":"Large", "diameter":14, "slicesPerPizza":8, "sliceCalories":360},
          {"size":"Extra Large", "diameter":16, "slicesPerPizza":10, "sliceCalories":370}
        ]
      },
      {"name":"Sausage",
        "image": "https://wasimpizza.com/wp-content/uploads/2022/02/pizza.png",
        "sizes": [
          {"size":"Eight Inch", "diameter":8, "slicesPerPizza":4, "sliceCalories":230},
          {"size":"Small", "diameter":10, "slicesPerPizza":6, "sliceCalories":220},
          {"size":"Medium", "diameter":12, "slicesPerPizza":8, "sliceCalories":240},
          {"size":"Large", "diameter":14, "slicesPerPizza":8, "sliceCalories":330},
          {"size":"Extra Large", "diameter":16, "slicesPerPizza":10, "sliceCalories":340}
        ]
      },
      {"name":"Garden Fresh",
        "image": "https://wasimpizza.com/wp-content/uploads/2022/02/pizza.png",
        "sizes": [
          {"size":"Eight Inch", "diameter":8, "slicesPerPizza":4, "sliceCalories":210},
          {"size":"Small", "diameter":10, "slicesPerPizza":6, "sliceCalories":200},
          {"size":"Medium", "diameter":12, "slicesPerPizza":8, "sliceCalories":220},
          {"size":"Large", "diameter":14, "slicesPerPizza":8, "sliceCalories":300},
          {"size":"Extra Large", "diameter":16, "slicesPerPizza":10, "sliceCalories":320}
        ]
      }
    ]
  },
  {
    "restaurant":"Dominos",
    "image": "https://wasimpizza.com/wp-content/uploads/2022/02/pizza.png",
    "address": "North California , Street 123, USA",
    "pizzaSelections":[
      {"name":"Cheese",
        "image": "https://wasimpizza.com/wp-content/uploads/2022/02/pizza.png",
        "sizes": [
          {"size":"Small", "diameter":10, "slicesPerPizza":6, "sliceCalories":200},
          {"size":"Medium", "diameter":12, "slicesPerPizza":8, "sliceCalories":210},
          {"size":"Large", "diameter":14, "slicesPerPizza":8, "sliceCalories":290},
          {"size":"Extra Large", "diameter":16, "slicesPerPizza":8, "sliceCalories":380}
        ]
      },
      {"name":"Pepperoni",
        "image": "https://wasimpizza.com/wp-content/uploads/2022/02/pizza.png",
        "sizes": [
          {"size":"Small", "diameter":10, "slicesPerPizza":6, "sliceCalories":210},
          {"size":"Medium", "diameter":12, "slicesPerPizza":8, "sliceCalories":220},
          {"size":"Large", "diameter":14, "slicesPerPizza":8, "sliceCalories":300},
          {"size":"Extra Large", "diameter":16, "slicesPerPizza":8, "sliceCalories":390}
        ]
      },
      {"name":"Sausage",
        "image": "https://wasimpizza.com/wp-content/uploads/2022/02/pizza.png",
        "sizes": [
          {"size":"Small", "diameter":10, "slicesPerPizza":6, "sliceCalories":230},
          {"size":"Medium", "diameter":12, "slicesPerPizza":8, "sliceCalories":240},
          {"size":"Large", "diameter":14, "slicesPerPizza":8, "sliceCalories":330},
          {"size":"Extra Large", "diameter":16, "slicesPerPizza":8, "sliceCalories":420}
        ]
      },
      {"name":"Spinach and Feta",
        "image": "https://wasimpizza.com/wp-content/uploads/2022/02/pizza.png",
        "sizes": [
          {"size":"Small", "diameter":10, "slicesPerPizza":6, "sliceCalories":220},
          {"size":"Medium", "diameter":12, "slicesPerPizza":8, "sliceCalories":240},
          {"size":"Large", "diameter":14, "slicesPerPizza":8, "sliceCalories":320},
          {"size":"Extra Large", "diameter":16, "slicesPerPizza":8, "sliceCalories":410}
        ]
      },
      {"name":"Deluxe",
        "image": "https://wasimpizza.com/wp-content/uploads/2022/02/pizza.png",
        "sizes": [
          {"size":"Small", "diameter":10, "slicesPerPizza":6, "sliceCalories":220},
          {"size":"Medium", "diameter":12, "slicesPerPizza":8, "sliceCalories":230},
          {"size":"Large", "diameter":14, "slicesPerPizza":8, "sliceCalories":320},
          {"size":"Extra Large", "diameter":16, "slicesPerPizza":8, "sliceCalories":410}
        ]
      },
      {"name":"Spinach and Feta",
        "image": "https://wasimpizza.com/wp-content/uploads/2022/02/pizza.png",
        "sizes": [
          {"size":"Small", "diameter":10, "slicesPerPizza":6, "sliceCalories":220},
          {"size":"Medium", "diameter":12, "slicesPerPizza":8, "sliceCalories":240},
          {"size":"Large", "diameter":14, "slicesPerPizza":8, "sliceCalories":320},
          {"size":"Extra Large", "diameter":16, "slicesPerPizza":8, "sliceCalories":410}
        ]
      },
      {"name":"Philly Cheese Steak",
        "image": "https://wasimpizza.com/wp-content/uploads/2022/02/pizza.png",
        "sizes": [
          {"size":"Small", "diameter":10, "slicesPerPizza":6, "sliceCalories":220},
          {"size":"Medium", "diameter":12, "slicesPerPizza":8, "sliceCalories":230},
          {"size":"Large", "diameter":14, "slicesPerPizza":8, "sliceCalories":310},
          {"size":"Extra Large", "diameter":16, "slicesPerPizza":8, "sliceCalories":400}
        ]
      },
      {"name":"Spinach and Feta",
        "image": "https://wasimpizza.com/wp-content/uploads/2022/02/pizza.png",
        "sizes": [
          {"size":"Small", "diameter":10, "slicesPerPizza":6, "sliceCalories":220},
          {"size":"Medium", "diameter":12, "slicesPerPizza":8, "sliceCalories":240},
          {"size":"Large", "diameter":14, "slicesPerPizza":8, "sliceCalories":320},
          {"size":"Extra Large", "diameter":16, "slicesPerPizza":8, "sliceCalories":410}
        ]
      },
      {"name":"Buffalo Chicken",
        "image": "https://wasimpizza.com/wp-content/uploads/2022/02/pizza.png",
        "sizes": [
          {"size":"Small", "diameter":10, "slicesPerPizza":6, "sliceCalories":240},
          {"size":"Medium", "diameter":12, "slicesPerPizza":8, "sliceCalories":260},
          {"size":"Large", "diameter":14, "slicesPerPizza":8, "sliceCalories":340},
          {"size":"Extra Large", "diameter":16, "slicesPerPizza":8, "sliceCalories":450}
        ]
      },
      {"name":"Cali Chicken Bacon Ranch",
        "image": "https://wasimpizza.com/wp-content/uploads/2022/02/pizza.png",
        "sizes": [
          {"size":"Small", "diameter":10, "slicesPerPizza":6, "sliceCalories":270},
          {"size":"Medium", "diameter":12, "slicesPerPizza":8, "sliceCalories":300},
          {"size":"Large", "diameter":14, "slicesPerPizza":8, "sliceCalories":400},
          {"size":"Extra Large", "diameter":16, "slicesPerPizza":8, "sliceCalories":520}
        ]
      },
      {"name":"Honolulu Hawaiian",
        "image": "https://wasimpizza.com/wp-content/uploads/2022/02/pizza.png",
        "sizes": [
          {"size":"Small", "diameter":10, "slicesPerPizza":6, "sliceCalories":230},
          {"size":"Medium", "diameter":12, "slicesPerPizza":8, "sliceCalories":240},
          {"size":"Large", "diameter":14, "slicesPerPizza":8, "sliceCalories":330},
          {"size":"Extra Large", "diameter":16, "slicesPerPizza":8, "sliceCalories":430}
        ]
      },
      {"name":"Hawaiian",
        "correctedTerm":"Honolulu Hawaiian",
        "image": "https://wasimpizza.com/wp-content/uploads/2022/02/pizza.png",
        "sizes": [
          {"size":"Small", "diameter":10, "slicesPerPizza":6, "sliceCalories":230},
          {"size":"Medium", "diameter":12, "slicesPerPizza":8, "sliceCalories":240},
          {"size":"Large", "diameter":14, "slicesPerPizza":8, "sliceCalories":330},
          {"size":"Extra Large", "diameter":16, "slicesPerPizza":8, "sliceCalories":430}
        ]
      },
      {"name":"Memphis BBQ Chicken",
        "image": "https://wasimpizza.com/wp-content/uploads/2022/02/pizza.png",
        "sizes": [
          {"size":"Small", "diameter":10, "slicesPerPizza":6, "sliceCalories":240},
          {"size":"Medium", "diameter":12, "slicesPerPizza":8, "sliceCalories":260},
          {"size":"Large", "diameter":14, "slicesPerPizza":8, "sliceCalories":350},
          {"size":"Extra Large", "diameter":16, "slicesPerPizza":8, "sliceCalories":450}
        ]
      },
      {"name":"Pacific Veggie",
        "image": "https://wasimpizza.com/wp-content/uploads/2022/02/pizza.png",
        "sizes": [
          {"size":"Small", "diameter":10, "slicesPerPizza":6, "sliceCalories":210},
          {"size":"Medium", "diameter":12, "slicesPerPizza":8, "sliceCalories":230},
          {"size":"Large", "diameter":14, "slicesPerPizza":8, "sliceCalories":310},
          {"size":"Extra Large", "diameter":16, "slicesPerPizza":8, "sliceCalories":390}
        ]
      },
      {"name":"Wisconsin 6 Cheese",
        "image": "https://wasimpizza.com/wp-content/uploads/2022/02/pizza.png",
        "sizes": [
          {"size":"Small", "diameter":10, "slicesPerPizza":6, "sliceCalories":220},
          {"size":"Medium", "diameter":12, "slicesPerPizza":8, "sliceCalories":250},
          {"size":"Large", "diameter":14, "slicesPerPizza":8, "sliceCalories":340},
          {"size":"Extra Large", "diameter":16, "slicesPerPizza":8, "sliceCalories":440}
        ]
      },
      {"name":"Extravaganzza",
        "image": "https://wasimpizza.com/wp-content/uploads/2022/02/pizza.png",
        "sizes": [
          {"size":"Small", "diameter":10, "slicesPerPizza":6, "sliceCalories":260},
          {"size":"Medium", "diameter":12, "slicesPerPizza":8, "sliceCalories":280},
          {"size":"Large", "diameter":14, "slicesPerPizza":8, "sliceCalories":390},
          {"size":"Extra Large", "diameter":16, "slicesPerPizza":8, "sliceCalories":510}
        ]
      },
      {"name":"Meatzza",
        "image": "https://wasimpizza.com/wp-content/uploads/2022/02/pizza.png",
        "sizes": [
          {"size":"Small", "diameter":10, "slicesPerPizza":6, "sliceCalories":260},
          {"size":"Medium", "diameter":12, "slicesPerPizza":8, "sliceCalories":270},
          {"size":"Large", "diameter":14, "slicesPerPizza":8, "sliceCalories":370},
          {"size":"Extra Large", "diameter":16, "slicesPerPizza":8, "sliceCalories":490}
        ]
      },
      {"name":"Ultimate Pepperoni",
        "image": "https://wasimpizza.com/wp-content/uploads/2022/02/pizza.png",
        "sizes": [
          {"size":"Small", "diameter":10, "slicesPerPizza":6, "sliceCalories":250},
          {"size":"Medium", "diameter":12, "slicesPerPizza":8, "sliceCalories":270},
          {"size":"Large", "diameter":14, "slicesPerPizza":8, "sliceCalories":370},
          {"size":"Extra Large", "diameter":16, "slicesPerPizza":8, "sliceCalories":480}
        ]
      }
    ]
  },
  {
    "restaurant":"Little Caesars",
    "image": "https://wasimpizza.com/wp-content/uploads/2022/02/pizza.png",
    "address": "North California , Street 123, USA",
    "pizzaSelections":[
      {"name":"Cheese",
        "image": "https://wasimpizza.com/wp-content/uploads/2022/02/pizza.png",
        "sizes": [
          {"size":"Large", "diameter":14, "slicesPerPizza":8, "sliceCalories":250}
        ]
      },
      {"name":"Pepperoni",
        "image": "https://wasimpizza.com/wp-content/uploads/2022/02/pizza.png",
        "sizes": [
          {"size":"Large", "diameter":14, "slicesPerPizza":8, "sliceCalories":280}
        ]
      },
      {"name":"Ultimate Supreme",
        "image": "https://wasimpizza.com/wp-content/uploads/2022/02/pizza.png",
        "sizes": [
          {"size":"Large", "diameter":14, "slicesPerPizza":8, "sliceCalories":300}
        ]
      },
      {"name":"3 Meat Treat",
        "image": "https://wasimpizza.com/wp-content/uploads/2022/02/pizza.png",
        "sizes": [
          {"size":"Large", "diameter":14, "slicesPerPizza":8, "sliceCalories":330}
        ]
      },
      {"name":"Hulu Hawaiian",
        "image": "https://wasimpizza.com/wp-content/uploads/2022/02/pizza.png",
        "sizes": [
          {"size":"Large", "diameter":14, "slicesPerPizza":8, "sliceCalories":270}
        ]
      },
      {"name":"Hawaiian",
        "correctedTerm":"Honolulu Hawaiian",
        "image": "https://wasimpizza.com/wp-content/uploads/2022/02/pizza.png",
        "sizes": [
          {"size":"Large", "diameter":14, "slicesPerPizza":8, "sliceCalories":270}
        ]
      },
      {"name":"Veggie",
        "image": "https://wasimpizza.com/wp-content/uploads/2022/02/pizza.png",
        "sizes": [
          {"size":"Large", "diameter":14, "slicesPerPizza":8, "sliceCalories":270}
        ]
      },
      {"name":"Italian Sausage",
        "image": "https://wasimpizza.com/wp-content/uploads/2022/02/pizza.png",
        "sizes": [
          {"size":"Large", "diameter":14, "slicesPerPizza":8, "sliceCalories":270}
        ]
      }
    ]
  },
  {
    "restaurant":"Pizza Hut",
    "image": "https://wasimpizza.com/wp-content/uploads/2022/02/pizza.png",
    "address": "North California , Street 123, USA",
    "pizzaSelections":[
      {"name":"Cheese",
        "image": "https://wasimpizza.com/wp-content/uploads/2022/02/pizza.png",
        "sizes": [
          {"size":"Small", "diameter":10, "slicesPerPizza":8, "sliceCalories":130},
          {"size":"Medium", "diameter":12, "slicesPerPizza":8, "sliceCalories":210},
          {"size":"Large", "diameter":14, "slicesPerPizza":8, "sliceCalories":290}
        ]
      },
      {"name":"Pepperoni",
        "image": "https://wasimpizza.com/wp-content/uploads/2022/02/pizza.png",
        "sizes": [
          {"size":"Small", "diameter":10, "slicesPerPizza":8, "sliceCalories":130},
          {"size":"Medium", "diameter":12, "slicesPerPizza":8, "sliceCalories":220},
          {"size":"Large", "diameter":14, "slicesPerPizza":8, "sliceCalories":300}
        ]
      },
      {"name":"Supreme",
        "image": "https://wasimpizza.com/wp-content/uploads/2022/02/pizza.png",
        "sizes": [
          {"size":"Small", "diameter":10, "slicesPerPizza":8, "sliceCalories":150},
          {"size":"Medium", "diameter":12, "slicesPerPizza":8, "sliceCalories":240},
          {"size":"Large", "diameter":14, "slicesPerPizza":8, "sliceCalories":330}
        ]
      },
      {"name":"Hawaiian Chicken",
        "image": "https://wasimpizza.com/wp-content/uploads/2022/02/pizza.png",
        "sizes": [
          {"size":"Small", "diameter":10, "slicesPerPizza":8, "sliceCalories":130},
          {"size":"Medium", "diameter":12, "slicesPerPizza":8, "sliceCalories":210},
          {"size":"Large", "diameter":14, "slicesPerPizza":8, "sliceCalories":290}
        ]
      },
      {"name":"Hawaiian",
        "correctedTerm":"Honolulu Hawaiian",
        "image": "https://wasimpizza.com/wp-content/uploads/2022/02/pizza.png",
        "sizes": [
          {"size":"Small", "diameter":10, "slicesPerPizza":8, "sliceCalories":130},
          {"size":"Medium", "diameter":12, "slicesPerPizza":8, "sliceCalories":210},
          {"size":"Large", "diameter":14, "slicesPerPizza":8, "sliceCalories":290}
        ]
      },
      {"name":"Italian Meatball",
        "image": "https://wasimpizza.com/wp-content/uploads/2022/02/pizza.png",
        "sizes": [
          {"size":"Small", "diameter":10, "slicesPerPizza":8, "sliceCalories":130},
          {"size":"Medium", "diameter":12, "slicesPerPizza":8, "sliceCalories":210},
          {"size":"Large", "diameter":14, "slicesPerPizza":8, "sliceCalories":290}
        ]
      },
      {"name":"Backyard BBQ Chicken",
        "image": "https://wasimpizza.com/wp-content/uploads/2022/02/pizza.png",
        "sizes": [
          {"size":"Small", "diameter":10, "slicesPerPizza":8, "sliceCalories":140},
          {"size":"Medium", "diameter":12, "slicesPerPizza":8, "sliceCalories":230},
          {"size":"Large", "diameter":14, "slicesPerPizza":8, "sliceCalories":330}
        ]
      },
      {"name":"Backyard BBQ",
        "correctedTerm":"Backyard BBQ Chicken",
        "image": "https://wasimpizza.com/wp-content/uploads/2022/02/pizza.png",
        "sizes": [
          {"size":"Small", "diameter":10, "slicesPerPizza":8, "sliceCalories":140},
          {"size":"Medium", "diameter":12, "slicesPerPizza":8, "sliceCalories":230},
          {"size":"Large", "diameter":14, "slicesPerPizza":8, "sliceCalories":330}
        ]
      },
      {"name":"Buffalo Chicken",
        "image": "https://wasimpizza.com/wp-content/uploads/2022/02/pizza.png",
        "sizes": [
          {"size":"Small", "diameter":10, "slicesPerPizza":8, "sliceCalories":130},
          {"size":"Medium", "diameter":12, "slicesPerPizza":8, "sliceCalories":210},
          {"size":"Large", "diameter":14, "slicesPerPizza":8, "sliceCalories":290}
        ]
      },
      {"name":"Meat Lovers",
        "image": "https://wasimpizza.com/wp-content/uploads/2022/02/pizza.png",
        "sizes": [
          {"size":"Small", "diameter":10, "slicesPerPizza":8, "sliceCalories":180},
          {"size":"Medium", "diameter":12, "slicesPerPizza":8, "sliceCalories":280},
          {"size":"Large", "diameter":14, "slicesPerPizza":8, "sliceCalories":390}
        ]
      },
      {"name":"BBQ Beef",
        "image": "https://wasimpizza.com/wp-content/uploads/2022/02/pizza.png",
        "sizes": [
          {"size":"Small", "diameter":10, "slicesPerPizza":8, "sliceCalories":140},
          {"size":"Medium", "diameter":12, "slicesPerPizza":8, "sliceCalories":240},
          {"size":"Large", "diameter":14, "slicesPerPizza":8, "sliceCalories":340}
        ]
      },
      {"name":"Veggie Lovers",
        "image": "https://wasimpizza.com/wp-content/uploads/2022/02/pizza.png",
        "sizes": [
          {"size":"Small", "diameter":10, "slicesPerPizza":8, "sliceCalories":120},
          {"size":"Medium", "diameter":12, "slicesPerPizza":8, "sliceCalories":200},
          {"size":"Large", "diameter":14, "slicesPerPizza":8, "sliceCalories":260}
        ]
      }
    ]
  }
]